{
    "meta": {
        "experiment_name": "medium_dual_ambiguity",
        "game_id": 7,
        "dialogue_pair": "InternVL3-78B-t0.0--InternVL3-78B-t0.0"
    },
    "players": {
        "GM": "Game master for escape_room",
        "Player 1 (Guide)": "Player 1 (Guide) (Guide): InternVL3-78B",
        "Player 2 (Explorer)": "Player 2 (Explorer) (Explorer): InternVL3-78B"
    },
    "turns": [
        [
            {
                "from": "GM",
                "to": "GM",
                "timestamp": "2025-07-20T12:47:46.323147",
                "action": {
                    "type": "image",
                    "content": {
                        "image": [
                            "https://www.ling.uni-potsdam.de/clembench/adk/images/ADE/training/work_place/reading_room/ADE_train_00015709.jpg"
                        ]
                    }
                }
            },
            {
                "from": "GM",
                "to": "Player 1 (Guide)",
                "timestamp": "2025-07-20T12:47:46.323355",
                "action": {
                    "type": "send message",
                    "content": "You are the GUIDE in MapWorld, a network of interconnected rooms.\n\nYour role is to assist me in reaching the ESCAPE ROOM.\nYou have access to a single image: the ESCAPE ROOM.\nI do not know what this room looks like.\nYou do not know the map layout or my current location.\n\nAt each step, you may only respond in one of the following formats:\n\n1. If I ask a question about the ESCAPE ROOM, reply strictly as:\nANSWER: your answer\n\n2. If I request a description of the ESCAPE ROOM, reply strictly as:\nDESCRIPTION: your description of the image\n\nDo not respond in any other format. Do not provide any commentary or clarification.\n\nLet\u2019s begin.\n\nPlease describe the ESCAPE ROOM using:\nDESCRIPTION: your description",
                    "label": "context"
                }
            },
            {
                "from": "Player 1 (Guide)",
                "to": "GM",
                "timestamp": "2025-07-20T12:48:21.057696",
                "action": {
                    "type": "get message",
                    "content": "DESCRIPTION: The ESCAPE ROOM is a cozy reading area with two maroon armchairs facing each other, a small wooden coffee table with a pink lamp, and a large bookshelf filled with magazines. There are plants around the room, and a window on the left side allows natural light to enter.",
                    "label": "response"
                }
            },
            {
                "from": "GM",
                "to": "GM",
                "timestamp": "2025-07-20T12:48:21.058150",
                "action": {
                    "type": "description",
                    "content": "guide"
                }
            },
            {
                "from": "GM",
                "to": "GM",
                "timestamp": "2025-07-20T12:48:21.058732",
                "action": {
                    "type": "image",
                    "content": {
                        "image": [
                            "https://www.ling.uni-potsdam.de/clembench/adk/images/ADE/training/home_or_hotel/home_office/ADE_train_00009395.jpg"
                        ]
                    }
                }
            },
            {
                "from": "GM",
                "to": "Player 2 (Explorer)",
                "timestamp": "2025-07-20T12:48:21.058776",
                "action": {
                    "type": "send message",
                    "content": "\nYou are the SEEKER in MapWorld, a network of interconnected rooms. Each room is shown to you as an image.\n\nYour objective is to navigate this environment and reach the ESCAPE ROOM.\n\nThere can be multiple rooms of the same type (e.g., a MapWorld with 4 rooms may contain 2 visually similar bathrooms).\nThese rooms might look nearly identical, but not exactly the same.\n\nI only have the image of the ESCAPE ROOM and will describe it to you. I do not know what room you are in, or how your\nroom's image looks like.\n\nAt each step, you will be shown an image of your current room.\n\nYou may perform only one of the following actions:\n\n1. If the current room exactly matches the ESCAPE ROOM based on my description, respond strictly with -\nESCAPE\n\n2. If the current room seems similar to the ESCAPE ROOM but you are uncertain, ask me a clarifying question that focuses on visually distinguishing\nfeatures that can help you tell your current room apart from the ESCAPE ROOM described.\nRespond strictly with -\nQUESTION: your question\n\n3. If the current room is definitely not the ESCAPE ROOM, choose a direction from the available options: ['west', 'east']\nreply strictly with -\nMOVE: chosen direction\n\nHere is the description of the ESCAPE ROOM:\ndescription: the escape room is a cozy reading area with two maroon armchairs facing each other, a small wooden coffee table with a pink lamp, and a large bookshelf filled with magazines. there are plants around the room, and a window on the left side allows natural light to enter\nWhat action do you choose?\n\nYou must follow the above format rules exactly.\nDo not respond in any other format. Do not provide any commentary or clarification.\n",
                    "label": "context"
                }
            },
            {
                "from": "Player 2 (Explorer)",
                "to": "GM",
                "timestamp": "2025-07-20T12:48:29.009693",
                "action": {
                    "type": "get message",
                    "content": "MOVE: west",
                    "label": "response"
                }
            },
            {
                "from": "GM",
                "to": "GM",
                "timestamp": "2025-07-20T12:48:29.011106",
                "action": {
                    "type": "image",
                    "content": {
                        "image": [
                            "https://www.ling.uni-potsdam.de/clembench/adk/images/ADE/training/work_place/reception/ADE_train_00015766.jpg"
                        ]
                    }
                }
            },
            {
                "from": "GM",
                "to": "Player 2 (Explorer)",
                "timestamp": "2025-07-20T12:48:29.011213",
                "action": {
                    "type": "send message",
                    "content": "Now you made a move to this room, you can choose one of the following three actions:\n\n1. If the current room exactly matches the ESCAPE ROOM based on my description, respond strictly with -\nESCAPE\n\n2. If the current room seems similar to the ESCAPE ROOM but you are uncertain, ask me a clarifying question that focuses on visually distinguishing\nfeatures that can help you tell your current room apart from the ESCAPE ROOM described.\nRespond strictly with -\nQUESTION: your question\n\n3. If the current room is definitely not the ESCAPE ROOM, choose a direction from the available options: ['north', 'east']\nreply strictly with -\nMOVE: chosen direction\n\nWhat action do you choose?\n\nYou must follow the above format rules exactly.\nDo not respond in any other format. Do not provide any commentary or clarification.\n",
                    "label": "context"
                }
            },
            {
                "from": "Player 2 (Explorer)",
                "to": "GM",
                "timestamp": "2025-07-20T12:48:31.634600",
                "action": {
                    "type": "get message",
                    "content": "MOVE: east",
                    "label": "response"
                }
            },
            {
                "from": "GM",
                "to": "GM",
                "timestamp": "2025-07-20T12:48:31.636246",
                "action": {
                    "type": "image",
                    "content": {
                        "image": [
                            "https://www.ling.uni-potsdam.de/clembench/adk/images/ADE/training/home_or_hotel/home_office/ADE_train_00009395.jpg"
                        ]
                    }
                }
            },
            {
                "from": "GM",
                "to": "Player 2 (Explorer)",
                "timestamp": "2025-07-20T12:48:31.636341",
                "action": {
                    "type": "send message",
                    "content": "Now you made a move to this room, you can choose one of the following three actions:\n\n1. If the current room exactly matches the ESCAPE ROOM based on my description, respond strictly with -\nESCAPE\n\n2. If the current room seems similar to the ESCAPE ROOM but you are uncertain, ask me a clarifying question that focuses on visually distinguishing\nfeatures that can help you tell your current room apart from the ESCAPE ROOM described.\nRespond strictly with -\nQUESTION: your question\n\n3. If the current room is definitely not the ESCAPE ROOM, choose a direction from the available options: ['west', 'east']\nreply strictly with -\nMOVE: chosen direction\n\nWhat action do you choose?\n\nYou must follow the above format rules exactly.\nDo not respond in any other format. Do not provide any commentary or clarification.\n",
                    "label": "context"
                }
            },
            {
                "from": "Player 2 (Explorer)",
                "to": "GM",
                "timestamp": "2025-07-20T12:48:40.348497",
                "action": {
                    "type": "get message",
                    "content": "MOVE: west",
                    "label": "response"
                }
            },
            {
                "from": "GM",
                "to": "GM",
                "timestamp": "2025-07-20T12:48:40.349734",
                "action": {
                    "type": "image",
                    "content": {
                        "image": [
                            "https://www.ling.uni-potsdam.de/clembench/adk/images/ADE/training/work_place/reception/ADE_train_00015766.jpg"
                        ]
                    }
                }
            },
            {
                "from": "GM",
                "to": "Player 2 (Explorer)",
                "timestamp": "2025-07-20T12:48:40.349863",
                "action": {
                    "type": "send message",
                    "content": "Now you made a move to this room, you can choose one of the following three actions:\n\n1. If the current room exactly matches the ESCAPE ROOM based on my description, respond strictly with -\nESCAPE\n\n2. If the current room seems similar to the ESCAPE ROOM but you are uncertain, ask me a clarifying question that focuses on visually distinguishing\nfeatures that can help you tell your current room apart from the ESCAPE ROOM described.\nRespond strictly with -\nQUESTION: your question\n\n3. If the current room is definitely not the ESCAPE ROOM, choose a direction from the available options: ['north', 'east']\nreply strictly with -\nMOVE: chosen direction\n\nWhat action do you choose?\n\nYou must follow the above format rules exactly.\nDo not respond in any other format. Do not provide any commentary or clarification.\n",
                    "label": "context"
                }
            },
            {
                "from": "Player 2 (Explorer)",
                "to": "GM",
                "timestamp": "2025-07-20T12:48:43.381818",
                "action": {
                    "type": "get message",
                    "content": "MOVE: north",
                    "label": "response"
                }
            },
            {
                "from": "GM",
                "to": "GM",
                "timestamp": "2025-07-20T12:48:43.383050",
                "action": {
                    "type": "image",
                    "content": {
                        "image": [
                            "https://www.ling.uni-potsdam.de/clembench/adk/images/ADE/training/work_place/reading_room/ADE_train_00015709.jpg"
                        ]
                    }
                }
            },
            {
                "from": "GM",
                "to": "Player 2 (Explorer)",
                "timestamp": "2025-07-20T12:48:43.383142",
                "action": {
                    "type": "send message",
                    "content": "Now you made a move to this room, you can choose one of the following three actions:\n\n1. If the current room exactly matches the ESCAPE ROOM based on my description, respond strictly with -\nESCAPE\n\n2. If the current room seems similar to the ESCAPE ROOM but you are uncertain, ask me a clarifying question that focuses on visually distinguishing\nfeatures that can help you tell your current room apart from the ESCAPE ROOM described.\nRespond strictly with -\nQUESTION: your question\n\n3. If the current room is definitely not the ESCAPE ROOM, choose a direction from the available options: ['east', 'south']\nreply strictly with -\nMOVE: chosen direction\n\nWhat action do you choose?\n\nYou must follow the above format rules exactly.\nDo not respond in any other format. Do not provide any commentary or clarification.\n",
                    "label": "context"
                }
            },
            {
                "from": "Player 2 (Explorer)",
                "to": "GM",
                "timestamp": "2025-07-20T12:48:52.805164",
                "action": {
                    "type": "get message",
                    "content": "MOVE: south",
                    "label": "response"
                }
            },
            {
                "from": "GM",
                "to": "GM",
                "timestamp": "2025-07-20T12:48:52.806826",
                "action": {
                    "type": "image",
                    "content": {
                        "image": [
                            "https://www.ling.uni-potsdam.de/clembench/adk/images/ADE/training/work_place/reception/ADE_train_00015766.jpg"
                        ]
                    }
                }
            },
            {
                "from": "GM",
                "to": "Player 2 (Explorer)",
                "timestamp": "2025-07-20T12:48:52.806918",
                "action": {
                    "type": "send message",
                    "content": "Now you made a move to this room, you can choose one of the following three actions:\n\n1. If the current room exactly matches the ESCAPE ROOM based on my description, respond strictly with -\nESCAPE\n\n2. If the current room seems similar to the ESCAPE ROOM but you are uncertain, ask me a clarifying question that focuses on visually distinguishing\nfeatures that can help you tell your current room apart from the ESCAPE ROOM described.\nRespond strictly with -\nQUESTION: your question\n\n3. If the current room is definitely not the ESCAPE ROOM, choose a direction from the available options: ['north', 'east']\nreply strictly with -\nMOVE: chosen direction\n\nWhat action do you choose?\n\nYou must follow the above format rules exactly.\nDo not respond in any other format. Do not provide any commentary or clarification.\n",
                    "label": "context"
                }
            },
            {
                "from": "Player 2 (Explorer)",
                "to": "GM",
                "timestamp": "2025-07-20T12:48:56.251751",
                "action": {
                    "type": "get message",
                    "content": "MOVE: north",
                    "label": "response"
                }
            },
            {
                "from": "GM",
                "to": "GM",
                "timestamp": "2025-07-20T12:48:56.253129",
                "action": {
                    "type": "image",
                    "content": {
                        "image": [
                            "https://www.ling.uni-potsdam.de/clembench/adk/images/ADE/training/work_place/reading_room/ADE_train_00015709.jpg"
                        ]
                    }
                }
            },
            {
                "from": "GM",
                "to": "Player 2 (Explorer)",
                "timestamp": "2025-07-20T12:48:56.253226",
                "action": {
                    "type": "send message",
                    "content": "Now you made a move to this room, you can choose one of the following three actions:\n\n1. If the current room exactly matches the ESCAPE ROOM based on my description, respond strictly with -\nESCAPE\n\n2. If the current room seems similar to the ESCAPE ROOM but you are uncertain, ask me a clarifying question that focuses on visually distinguishing\nfeatures that can help you tell your current room apart from the ESCAPE ROOM described.\nRespond strictly with -\nQUESTION: your question\n\n3. If the current room is definitely not the ESCAPE ROOM, choose a direction from the available options: ['east', 'south']\nreply strictly with -\nMOVE: chosen direction\n\nWhat action do you choose?\n\nYou must follow the above format rules exactly.\nDo not respond in any other format. Do not provide any commentary or clarification.\n",
                    "label": "context"
                }
            },
            {
                "from": "Player 2 (Explorer)",
                "to": "GM",
                "timestamp": "2025-07-20T12:49:06.449913",
                "action": {
                    "type": "get message",
                    "content": "MOVE: south",
                    "label": "response"
                }
            },
            {
                "from": "GM",
                "to": "GM",
                "timestamp": "2025-07-20T12:49:06.451172",
                "action": {
                    "type": "image",
                    "content": {
                        "image": [
                            "https://www.ling.uni-potsdam.de/clembench/adk/images/ADE/training/work_place/reception/ADE_train_00015766.jpg"
                        ]
                    }
                }
            },
            {
                "from": "GM",
                "to": "Player 2 (Explorer)",
                "timestamp": "2025-07-20T12:49:06.451265",
                "action": {
                    "type": "send message",
                    "content": "Now you made a move to this room, you can choose one of the following three actions:\n\n1. If the current room exactly matches the ESCAPE ROOM based on my description, respond strictly with -\nESCAPE\n\n2. If the current room seems similar to the ESCAPE ROOM but you are uncertain, ask me a clarifying question that focuses on visually distinguishing\nfeatures that can help you tell your current room apart from the ESCAPE ROOM described.\nRespond strictly with -\nQUESTION: your question\n\n3. If the current room is definitely not the ESCAPE ROOM, choose a direction from the available options: ['north', 'east']\nreply strictly with -\nMOVE: chosen direction\n\nWhat action do you choose?\n\nYou must follow the above format rules exactly.\nDo not respond in any other format. Do not provide any commentary or clarification.\n",
                    "label": "context"
                }
            },
            {
                "from": "Player 2 (Explorer)",
                "to": "GM",
                "timestamp": "2025-07-20T12:49:10.366953",
                "action": {
                    "type": "get message",
                    "content": "MOVE: north",
                    "label": "response"
                }
            },
            {
                "from": "GM",
                "to": "GM",
                "timestamp": "2025-07-20T12:49:10.368616",
                "action": {
                    "type": "image",
                    "content": {
                        "image": [
                            "https://www.ling.uni-potsdam.de/clembench/adk/images/ADE/training/work_place/reading_room/ADE_train_00015709.jpg"
                        ]
                    }
                }
            },
            {
                "from": "GM",
                "to": "Player 2 (Explorer)",
                "timestamp": "2025-07-20T12:49:10.368708",
                "action": {
                    "type": "send message",
                    "content": "Now you made a move to this room, you can choose one of the following three actions:\n\n1. If the current room exactly matches the ESCAPE ROOM based on my description, respond strictly with -\nESCAPE\n\n2. If the current room seems similar to the ESCAPE ROOM but you are uncertain, ask me a clarifying question that focuses on visually distinguishing\nfeatures that can help you tell your current room apart from the ESCAPE ROOM described.\nRespond strictly with -\nQUESTION: your question\n\n3. If the current room is definitely not the ESCAPE ROOM, choose a direction from the available options: ['east', 'south']\nreply strictly with -\nMOVE: chosen direction\n\nWhat action do you choose?\n\nYou must follow the above format rules exactly.\nDo not respond in any other format. Do not provide any commentary or clarification.\n",
                    "label": "context"
                }
            },
            {
                "from": "Player 2 (Explorer)",
                "to": "GM",
                "timestamp": "2025-07-20T12:49:21.101426",
                "action": {
                    "type": "get message",
                    "content": "MOVE: south",
                    "label": "response"
                }
            },
            {
                "from": "GM",
                "to": "GM",
                "timestamp": "2025-07-20T12:49:21.102670",
                "action": {
                    "type": "image",
                    "content": {
                        "image": [
                            "https://www.ling.uni-potsdam.de/clembench/adk/images/ADE/training/work_place/reception/ADE_train_00015766.jpg"
                        ]
                    }
                }
            },
            {
                "from": "GM",
                "to": "Player 2 (Explorer)",
                "timestamp": "2025-07-20T12:49:21.102763",
                "action": {
                    "type": "send message",
                    "content": "Now you made a move to this room, you can choose one of the following three actions:\n\n1. If the current room exactly matches the ESCAPE ROOM based on my description, respond strictly with -\nESCAPE\n\n2. If the current room seems similar to the ESCAPE ROOM but you are uncertain, ask me a clarifying question that focuses on visually distinguishing\nfeatures that can help you tell your current room apart from the ESCAPE ROOM described.\nRespond strictly with -\nQUESTION: your question\n\n3. If the current room is definitely not the ESCAPE ROOM, choose a direction from the available options: ['north', 'east']\nreply strictly with -\nMOVE: chosen direction\n\nWhat action do you choose?\n\nYou must follow the above format rules exactly.\nDo not respond in any other format. Do not provide any commentary or clarification.\n",
                    "label": "context"
                }
            },
            {
                "from": "Player 2 (Explorer)",
                "to": "GM",
                "timestamp": "2025-07-20T12:49:25.660349",
                "action": {
                    "type": "get message",
                    "content": "MOVE: north",
                    "label": "response"
                }
            },
            {
                "from": "GM",
                "to": "GM",
                "timestamp": "2025-07-20T12:49:25.661589",
                "action": {
                    "type": "image",
                    "content": {
                        "image": [
                            "https://www.ling.uni-potsdam.de/clembench/adk/images/ADE/training/work_place/reading_room/ADE_train_00015709.jpg"
                        ]
                    }
                }
            },
            {
                "from": "GM",
                "to": "Player 2 (Explorer)",
                "timestamp": "2025-07-20T12:49:25.661698",
                "action": {
                    "type": "send message",
                    "content": "Now you made a move to this room, you can choose one of the following three actions:\n\n1. If the current room exactly matches the ESCAPE ROOM based on my description, respond strictly with -\nESCAPE\n\n2. If the current room seems similar to the ESCAPE ROOM but you are uncertain, ask me a clarifying question that focuses on visually distinguishing\nfeatures that can help you tell your current room apart from the ESCAPE ROOM described.\nRespond strictly with -\nQUESTION: your question\n\n3. If the current room is definitely not the ESCAPE ROOM, choose a direction from the available options: ['east', 'south']\nreply strictly with -\nMOVE: chosen direction\n\nWhat action do you choose?\n\nYou must follow the above format rules exactly.\nDo not respond in any other format. Do not provide any commentary or clarification.\n",
                    "label": "context"
                }
            },
            {
                "from": "Player 2 (Explorer)",
                "to": "GM",
                "timestamp": "2025-07-20T12:49:37.787272",
                "action": {
                    "type": "get message",
                    "content": "MOVE: south",
                    "label": "response"
                }
            },
            {
                "from": "GM",
                "to": "GM",
                "timestamp": "2025-07-20T12:49:37.788885",
                "action": {
                    "type": "image",
                    "content": {
                        "image": [
                            "https://www.ling.uni-potsdam.de/clembench/adk/images/ADE/training/work_place/reception/ADE_train_00015766.jpg"
                        ]
                    }
                }
            },
            {
                "from": "GM",
                "to": "Player 2 (Explorer)",
                "timestamp": "2025-07-20T12:49:37.788976",
                "action": {
                    "type": "send message",
                    "content": "Now you made a move to this room, you can choose one of the following three actions:\n\n1. If the current room exactly matches the ESCAPE ROOM based on my description, respond strictly with -\nESCAPE\n\n2. If the current room seems similar to the ESCAPE ROOM but you are uncertain, ask me a clarifying question that focuses on visually distinguishing\nfeatures that can help you tell your current room apart from the ESCAPE ROOM described.\nRespond strictly with -\nQUESTION: your question\n\n3. If the current room is definitely not the ESCAPE ROOM, choose a direction from the available options: ['north', 'east']\nreply strictly with -\nMOVE: chosen direction\n\nWhat action do you choose?\n\nYou must follow the above format rules exactly.\nDo not respond in any other format. Do not provide any commentary or clarification.\n",
                    "label": "context"
                }
            },
            {
                "from": "Player 2 (Explorer)",
                "to": "GM",
                "timestamp": "2025-07-20T12:49:42.904051",
                "action": {
                    "type": "get message",
                    "content": "MOVE: north",
                    "label": "response"
                }
            },
            {
                "from": "GM",
                "to": "GM",
                "timestamp": "2025-07-20T12:49:42.905247",
                "action": {
                    "type": "image",
                    "content": {
                        "image": [
                            "https://www.ling.uni-potsdam.de/clembench/adk/images/ADE/training/work_place/reading_room/ADE_train_00015709.jpg"
                        ]
                    }
                }
            },
            {
                "from": "GM",
                "to": "Player 2 (Explorer)",
                "timestamp": "2025-07-20T12:49:42.905353",
                "action": {
                    "type": "send message",
                    "content": "Now you made a move to this room, you can choose one of the following three actions:\n\n1. If the current room exactly matches the ESCAPE ROOM based on my description, respond strictly with -\nESCAPE\n\n2. If the current room seems similar to the ESCAPE ROOM but you are uncertain, ask me a clarifying question that focuses on visually distinguishing\nfeatures that can help you tell your current room apart from the ESCAPE ROOM described.\nRespond strictly with -\nQUESTION: your question\n\n3. If the current room is definitely not the ESCAPE ROOM, choose a direction from the available options: ['east', 'south']\nreply strictly with -\nMOVE: chosen direction\n\nWhat action do you choose?\n\nYou must follow the above format rules exactly.\nDo not respond in any other format. Do not provide any commentary or clarification.\n",
                    "label": "context"
                }
            },
            {
                "from": "Player 2 (Explorer)",
                "to": "GM",
                "timestamp": "2025-07-20T12:49:55.912475",
                "action": {
                    "type": "get message",
                    "content": "MOVE: south",
                    "label": "response"
                }
            },
            {
                "from": "GM",
                "to": "GM",
                "timestamp": "2025-07-20T12:49:55.913975",
                "action": {
                    "type": "image",
                    "content": {
                        "image": [
                            "https://www.ling.uni-potsdam.de/clembench/adk/images/ADE/training/work_place/reception/ADE_train_00015766.jpg"
                        ]
                    }
                }
            },
            {
                "from": "GM",
                "to": "Player 2 (Explorer)",
                "timestamp": "2025-07-20T12:49:55.914066",
                "action": {
                    "type": "send message",
                    "content": "Now you made a move to this room, you can choose one of the following three actions:\n\n1. If the current room exactly matches the ESCAPE ROOM based on my description, respond strictly with -\nESCAPE\n\n2. If the current room seems similar to the ESCAPE ROOM but you are uncertain, ask me a clarifying question that focuses on visually distinguishing\nfeatures that can help you tell your current room apart from the ESCAPE ROOM described.\nRespond strictly with -\nQUESTION: your question\n\n3. If the current room is definitely not the ESCAPE ROOM, choose a direction from the available options: ['north', 'east']\nreply strictly with -\nMOVE: chosen direction\n\nWhat action do you choose?\n\nYou must follow the above format rules exactly.\nDo not respond in any other format. Do not provide any commentary or clarification.\n",
                    "label": "context"
                }
            },
            {
                "from": "Player 2 (Explorer)",
                "to": "GM",
                "timestamp": "2025-07-20T12:50:01.695765",
                "action": {
                    "type": "get message",
                    "content": "MOVE: north",
                    "label": "response"
                }
            },
            {
                "from": "GM",
                "to": "GM",
                "timestamp": "2025-07-20T12:50:01.696121",
                "action": {
                    "type": "turns exceeded",
                    "content": "failed game: explorer"
                }
            }
        ]
    ]
}